MANIFEST.in
README.rst
setup.py
spykeviewer/__init__.py
spykeviewer/api.py
spykeviewer/splash_rc.py
spykeviewer/start.py
spykeviewer.egg-info/PKG-INFO
spykeviewer.egg-info/SOURCES.txt
spykeviewer.egg-info/dependency_links.txt
spykeviewer.egg-info/entry_points.txt
spykeviewer.egg-info/not-zip-safe
spykeviewer.egg-info/requires.txt
spykeviewer.egg-info/top_level.txt
spykeviewer/plugin_framework/__init__.py
spykeviewer/plugin_framework/data_provider_viewer.py
spykeviewer/plugin_framework/filter_manager.py
spykeviewer/plugin_framework/plugin_manager.py
spykeviewer/plugins/Raw Data/signal.py
spykeviewer/plugins/Raw Data/spectogram.py
spykeviewer/plugins/Raw Data/spikes.py
spykeviewer/plugins/Spike Trains/correlogram.py
spykeviewer/plugins/Spike Trains/interspike_intervals.py
spykeviewer/plugins/Spike Trains/psth.py
spykeviewer/plugins/Spike Trains/raster_plot.py
spykeviewer/plugins/Spike Trains/sde.py
spykeviewer/tests/__init__.py
spykeviewer/tests/test_main_window.py
spykeviewer/tests/test_plugin_manager.py
spykeviewer/ui/__init__.py
spykeviewer/ui/checkable_item_delegate.py
spykeviewer/ui/dir_files_dialog.py
spykeviewer/ui/filter_dialog.py
spykeviewer/ui/filter_dock.py
spykeviewer/ui/filter_group_dialog.py
spykeviewer/ui/icons_rc.py
spykeviewer/ui/io_settings.py
spykeviewer/ui/ipython_connection.py
spykeviewer/ui/main_ui.py
spykeviewer/ui/main_window.py
spykeviewer/ui/main_window_neo.py
spykeviewer/ui/neo_navigation.py
spykeviewer/ui/neo_navigation_ui.py
spykeviewer/ui/plugin_editor_dock.py
spykeviewer/ui/plugin_model.py
spykeviewer/ui/remote_thread.py
spykeviewer/ui/settings.py
spykeviewer/ui/settings_ui.py