Metadata-Version: 1.1
Name: spykeviewer
Version: 0.4.0
Summary: A multi-platform GUI application for navigating, analyzing and visualizing electrophysiological datasets
Home-page: https://github.com/rproepp/spykeviewer
Author: Robert Pröpper
Author-email: UNKNOWN
License: BSD
Platform: UNKNOWN
Classifier: Development Status :: 4 - Beta
Classifier: Intended Audience :: Science/Research
Classifier: License :: OSI Approved :: BSD License
Classifier: Natural Language :: English
Classifier: Operating System :: OS Independent
Classifier: Programming Language :: Python
Classifier: Topic :: Scientific/Engineering :: Bio-Informatics
